pymorlocinternals/__init__.py
pymorlocinternals/main.py
pymorlocinternals/types.py
pymorlocinternals/version.py
pymorlocinternals-0.5.0.dist-info/METADATA
pymorlocinternals-0.5.0.dist-info/WHEEL
pymorlocinternals-0.5.0.dist-info/top_level.txt
pymorlocinternals-0.5.0.dist-info/RECORD
