Metadata-Version: 2.1
Name: pymorlocinternals
Version: 0.5.0
Summary: Python serialization code for morloc interoperability
Home-page: https://github.com/morloc-project/pymorlocinternals
Author: Zebulun Arendsee
Author-email: zbwrnz@gmail.com
Classifier: Programming Language :: Python :: 3
Classifier: License :: OSI Approved :: MIT License
Classifier: Operating System :: OS Independent
